hotlib/__init__.py
hotlib/georeferencing.py
hotlib/utils.py
hotlib/inference/__init__.py
hotlib/inference/predict.py
hotlib/inference/utils.py
hotlib/postprocessing/__init__.py
hotlib/postprocessing/building_footprint.py
hotlib/postprocessing/get_polygons.py
hotlib/postprocessing/merge_polygons.py
hotlib/postprocessing/polygonize.py
hotlib/postprocessing/utils.py
hotlib/postprocessing/vectorize.py
hotlib/preprocessing/__init__.py
hotlib/preprocessing/clip_labels.py
hotlib/preprocessing/fix_labels.py
hotlib/preprocessing/preprocess.py
hotlib/preprocessing/reproject_labels.py
hotlib-1.0.33.dist-info/LICENSE
hotlib-1.0.33.dist-info/METADATA
hotlib-1.0.33.dist-info/WHEEL
hotlib-1.0.33.dist-info/top_level.txt
hotlib-1.0.33.dist-info/RECORD
