Metadata-Version: 2.1
Name: hotlib
Version: 1.0.33
Summary: Utilities for an AI-assisted mapping tool developed for HOT.
Author-email: Omdena <project@omdena.com>
License: MIT License
Project-URL: repository, https://dagshub.com/Omdena/HOT
Keywords: preprocessing,inference,postprocessing,stitching
Classifier: License :: OSI Approved :: MIT License
Classifier: Programming Language :: Python :: 3
Requires-Python: >=3.7
License-File: LICENSE
Requires-Dist: shapely
Requires-Dist: GDAL
Requires-Dist: numpy
Requires-Dist: tensorflow
Requires-Dist: Pillow
Requires-Dist: geopandas
Requires-Dist: rasterio
Requires-Dist: mercantile
Requires-Dist: tqdm
Requires-Dist: rtree
Requires-Dist: opencv-python
Provides-Extra: build
Requires-Dist: build ; extra == 'build'
Requires-Dist: twine ; extra == 'build'
Provides-Extra: dev
Requires-Dist: black ; extra == 'dev'
Requires-Dist: bumpver ; extra == 'dev'
Requires-Dist: isort ; extra == 'dev'
